{
  "version": 1,
  "id": "studio_one",
  "label": "Studio One",
  "description": "Shortcuts aligned with PreSonus Studio One defaults where commands overlap.",
  "sourceMenuVersion": 1,
  "generatedAt": "2026-05-30T05:03:52.119Z",
  "bindings": {
    "project:new": "Ctrl+N",
    "project:new-from-template": "Ctrl+Shift+N",
    "project:open": "Ctrl+O",
    "project:save": "Ctrl+S",
    "project:save-as": "Ctrl+Shift+S",
    "project:snapshot": "Ctrl+Alt+S",
    "file:import-audio": "Ctrl+I",
    "file:export-audio": "Ctrl+E",
    "file:export-stems": "Ctrl+Shift+E",
    "project:close": "Ctrl+W",
    "app:quit": "Alt+F4",
    "edit:undo": "Ctrl+Z",
    "edit:redo": "Ctrl+Y",
    "edit:cut": "Ctrl+X",
    "edit:copy": "Ctrl+C",
    "edit:paste": "Ctrl+V",
    "edit:duplicate": "D",
    "edit:delete": "Delete",
    "edit:select-all": "Ctrl+A",
    "edit:deselect-all": "Ctrl+D",
    "clip:split-at-playhead": "Alt+X",
    "clip:consolidate": "Ctrl+J",
    "timeline:toggle-snap": "N",
    "app:preferences": "Ctrl+,",
    "midi:select-all": "Ctrl+A",
    "midi:delete-selected": "Delete",
    "midi:duplicate-selected": "Ctrl+D",
    "midi:quantize": "Q",
    "midi:nudge-left": "Alt+ArrowLeft",
    "midi:nudge-right": "Alt+ArrowRight",
    "midi:transpose-up": "Shift+ArrowUp",
    "midi:transpose-down": "Shift+ArrowDown",
    "midi:transpose-octave-up": "Ctrl+Shift+ArrowUp",
    "midi:transpose-octave-down": "Ctrl+Shift+ArrowDown",
    "project:settings": "Ctrl+.",
    "track:show-add-dialog": "T",
    "track:add-midi": "Ctrl+Shift+T",
    "transport:play-pause": "Space",
    "transport:stop": "Numpad0",
    "transport:record": "Numpad*",
    "transport:toggle-loop": "Numpad/",
    "transport:toggle-metronome": "K",
    "transport:go-to-start": "Numpad,",
    "transport:go-to-end": "End",
    "transport:rewind": "Numpad-",
    "transport:fast-forward": "Numpad+",
    "audio:create-crossfade": "X",
    "audio:bounce-in-place": "Ctrl+B",
    "audio:render-selection": "Ctrl+R",
    "automation:delete-selected-points": "Delete",
    "window:minimize": "Ctrl+M",
    "window:toggle-fullscreen": "F11",
    "panel:toggle-browser": "F5",
    "panel:toggle-inspector": "F4",
    "panel:toggle-mixer": "F3",
    "panel:toggle-device-panel": "Ctrl+4",
    "panel:toggle-midi-editor": "F2",
    "panel:toggle-automation": "Ctrl+6",
    "view:zoom-in": "Ctrl+=",
    "view:zoom-out": "Ctrl+-",
    "view:reset-zoom": "Ctrl+0",
    "tools:select-pointer": "1",
    "tools:select-pen": "5",
    "tools:select-cut": "3",
    "tools:select-automation": "A",
    "tools:quick-search": "Ctrl+P",
    "tools:developer-tools": "Ctrl+Shift+I",
    "app:force-reload": "Ctrl+Shift+R",
    "help:documentation": "F1",
    "help:keyboard-shortcuts": "Ctrl+/"
  }
}
